Workbook

Sheet Инструкция
B2: Wordstat — оценка спроса, проект «Чита»
B4: Что это | C4: Шаблон для снятия частотности поисковых запросов и превращения её в решение по сегменту проекта. Заполняется вручную либо автоматически скриптом collect.py.
B6: НАСТРОЙКИ СБОРА
B7: Регионы | C7: Снимать по каждому запросу трижды: Чита (город), Забайкальский край, Иркутск (контроль). Без контрольного региона цифры не с чем сравнить.
B8: Период | C8: Последние 30 дней для частотности. Отдельно — 24 месяца помесячно на листе «Динамика».
B9: Соответствие | C9: Три колонки на регион: широкое, "фраза", "!точная !форма". Разрыв между широким и фразовым показывает долю мусора.
B10: Устройства | C10: Все. Отдельно мобайл снимать не нужно на этом этапе.
B12: ЧТО ЗАПОЛНЯТЬ
B13: Жёлтые ячейки | C13: Только их. Всё остальное — формулы, их не трогать.
B14: «Меньше 10» | C14: Ставить 0. Это не пропуск данных, а результат: по категорийным запросам ноль — главный вывод исследования.
B16: ПОРЯДОК РАБОТЫ
B17: 1 | C17: Заполнить лист «Данные» — все три региона.
B18: 2 | C18: Заполнить лист «Динамика» по 8 опорным запросам.
B19: 3 | C19: Открыть лист «Свод» — расчёты и вердикты появятся сами.
B20: 4 | C20: Прочитать лист «Пороги решения» и сверить с фактическими цифрами.
B21: 5 | C21: Повторить сбор через 3 и 6 месяцев в копии файла — динамика важнее среза.
B23: ВАЖНО ПРИ ЧТЕНИИ
B24: Экспозиция ≠ спрос | C24: Частотность показывает интерес, а не платёжеспособность. Сверять с данными Росреестра по фактическим сделкам.
B25: Низкий спрос ≠ нет рынка | C25: В категории без ментальной доступности поиска нет по определению. Ноль по блоку A означает «категорию надо создавать», а не «проект не нужен».
B26: Источник | C26: Yandex Wordstat, Wordstat API в составе Yandex Search API. Дата сбора обязательна — данные меняются.
B28: Дата сбора:
B29: Кто собирал:

Sheet Данные
A1: Блок | B1: Поисковый запрос | C1: Чита широкое | D1: Чита "фраза" | E1: Чита "!точное" | F1: Забайкальский край широкое | G1: Забайкальский край "фраза" | H1: Иркутск широкое | I1: Иркутск "фраза" | J1: Комментарий
A2: A. Категория | B2: коттеджный поселок чита
A3: A. Категория | B3: коттеджные поселки читы
A4: A. Категория | B4: поселок бизнес класса чита
A5: A. Категория | B5: закрытый поселок чита
A6: A. Категория | B6: организованный коттеджный поселок чита
A7: A. Категория | B7: таунхаус чита
A8: A. Категория | B8: загородная недвижимость чита
A9: A. Категория | B9: загородный поселок забайкальский край
A10: B. Продукт | B10: купить дом чита
A11: B. Продукт | B11: купить дом в чите с участком
A12: B. Продукт | B12: дом чита пригород
A13: B. Продукт | B13: готовый дом под ключ чита
... A84: J. Бренды конкурентов | B84: солар чита поселок
B86: ПРИМЕР заполнения (удалить): | C86: 1240 | D86: 310 | E86: 95 | F86: 1890 | G86: 460 | H86: 8400 | I86: 2100 | J86: «Меньше 10» ставить как 0

Sheet Динамика
A1: Помесячная динамика, регион Чита, 24 месяца
A3: Месяц | B3: коттеджный поселок чита | C3: купить дом чита | D3: участок ижс чита | E3: дальневосточная ипотека чита | F3: построить дом чита | G3: купить квартиру чита | H3: дом карповка | I3: бурение скважин чита цена
A4: 09.2024
A5: 10.2024
A6: 11.2024
A7: 12.2024
A8: 01.2025
A9: 02.2025
A10: 03.2025
A11: 04.2025
A12: 05.2025
A13: 06.2025
A14: 07.2025
A15: 08.2025
... A27: 08.2026
A29: Среднее | B29: =IFERROR(AVERAGE(B4:B27),0) -> 0 | C29: =IFERROR(AVERAGE(C4:C27),0) -> 0 | D29: =IFERROR(AVERAGE(D4:D27),0) -> 0 | E29: =IFERROR(AVERAGE(E4:E27),0) -> 0 | F29: =IFERROR(AVERAGE(F4:F27),0) -> 0 | G29: =IFERROR(AVERAGE(G4:G27),0) -> 0 | H29: =IFERROR(AVERAGE(H4:H27),0) -> 0 | I29: =IFERROR(AVERAGE(I4:I27),0) -> 0
A30: Пик | B30: =IFERROR(MAX(B4:B27),0) -> 0 | C30: =IFERROR(MAX(C4:C27),0) -> 0 | D30: =IFERROR(MAX(D4:D27),0) -> 0 | E30: =IFERROR(MAX(E4:E27),0) -> 0 | F30: =IFERROR(MAX(F4:F27),0) -> 0 | G30: =IFERROR(MAX(G4:G27),0) -> 0 | H30: =IFERROR(MAX(H4:H27),0) -> 0 | I30: =IFERROR(MAX(I4:I27),0) -> 0
A31: Мин | B31: =IFERROR(MIN(B4:B27),0) -> 0 | C31: =IFERROR(MIN(C4:C27),0) -> 0 | D31: =IFERROR(MIN(D4:D27),0) -> 0 | E31: =IFERROR(MIN(E4:E27),0) -> 0 | F31: =IFERROR(MIN(F4:F27),0) -> 0 | G31: =IFERROR(MIN(G4:G27),0) -> 0 | H31: =IFERROR(MIN(H4:H27),0) -> 0 | I31: =IFERROR(MIN(I4:I27),0) -> 0
A32: Сезонный размах | B32: =IFERROR(B30/MAX(B31,1),0) -> 0 | C32: =IFERROR(C30/MAX(C31,1),0) -> 0 | D32: =IFERROR(D30/MAX(D31,1),0) -> 0 | E32: =IFERROR(E30/MAX(E31,1),0) -> 0 | F32: =IFERROR(F30/MAX(F31,1),0) -> 0 | G32: =IFERROR(G30/MAX(G31,1),0) -> 0 | H32: =IFERROR(H30/MAX(H31,1),0) -> 0 | I32: =IFERROR(I30/MAX(I31,1),0) -> 0
A33: Год к году, % | B33: =IFERROR(SUM(B16:B27)/MAX(SUM(B4:B15),1)-1,0) -> -1 | C33: =IFERROR(SUM(C16:C27)/MAX(SUM(C4:C15),1)-1,0) -> -1 | D33: =IFERROR(SUM(D16:D27)/MAX(SUM(D4:D15),1)-1,0) -> -1 | E33: =IFERROR(SUM(E16:E27)/MAX(SUM(E4:E15),1)-1,0) -> -1 | F33: =IFERROR(SUM(F16:F27)/MAX(SUM(F4:F15),1)-1,0) -> -1 | G33: =IFERROR(SUM(G16:G27)/MAX(SUM(G4:G15),1)-1,0) -> -1 | H33: =IFERROR(SUM(H16:H27)/MAX(SUM(H4:H15),1)-1,0) -> -1 | I33: =IFERROR(SUM(I16:I27)/MAX(SUM(I4:I15),1)-1,0) -> -1
A35: Сезонный размах ниже 1,5x по загородным запросам — признак того, что выраженного сезона нет, то есть спроса как явления тоже.

Sheet Свод
A1: Свод по блокам
A2: Все значения — формулы с листа «Данные». Заполнять здесь ничего не нужно.
A4: Блок | B4: Чита широкое | C4: Чита "фраза" | D4: Край широкое | E4: Иркутск широкое | F4: Чита / Иркутск | G4: Что это значит
A5: A. Категория | B5: =SUM(Данные!C2:C9) -> 0 | C5: =SUM(Данные!D2:D9) -> 0 | D5: =SUM(Данные!F2:F9) -> 0 | E5: =SUM(Данные!H2:H9) -> 0 | F5: =IFERROR(B5/MAX(E5,1),0) -> 0 | G5: Прямой замер mental availability. Если близко к нулю — категории в голове рынка нет.
A6: B. Продукт | B6: =SUM(Данные!C10:C20) -> 0 | C6: =SUM(Данные!D10:D20) -> 0 | D6: =SUM(Данные!F10:F20) -> 0 | E6: =SUM(Данные!H10:H20) -> 0 | F6: =IFERROR(B6/MAX(E6,1),0) -> 0 | G6: Реальный спрос на дом. Основной источник трафика на старте.
A7: C. Земля | B7: =SUM(Данные!C21:C27) -> 0 | C7: =SUM(Данные!D21:D27) -> 0 | D7: =SUM(Данные!F21:F27) -> 0 | E7: =SUM(Данные!H21:H27) -> 0 | F7: =IFERROR(B7/MAX(E7,1),0) -> 0 | G7: Конкурент №1 по бюджету: купить участок и строить самому.
A8: D. География | B8: =SUM(Данные!C28:C41) -> 0 | C8: =SUM(Данные!D28:D41) -> 0 | D8: =SUM(Данные!F28:F41) -> 0 | E8: =SUM(Данные!H28:H41) -> 0 | F8: =IFERROR(B8/MAX(E8,1),0) -> 0 | G8: Проверка локации. Сравнить Карповку со Смоленкой и Засопкой.
A9: E. Финансовые триггеры | B9: =SUM(Данные!C42:C50) -> 0 | C9: =SUM(Данные!D42:D50) -> 0 | D9: =SUM(Данные!F42:F50) -> 0 | E9: =SUM(Данные!H42:H50) -> 0 | F9: =IFERROR(B9/MAX(E9,1),0) -> 0 | G9: Опережающий индикатор намерения. Рост = формируется платёжеспособный спрос.
A10: F. Самострой и подряд | B10: =SUM(Данные!C51:C60) -> 0 | C10: =SUM(Данные!D51:D60) -> 0 | D10: =SUM(Данные!F51:F60) -> 0 | E10: =SUM(Данные!H51:H60) -> 0 | F10: =IFERROR(B10/MAX(E10,1),0) -> 0 | G10: Объём альтернативы «сделаю сам». Чем выше, тем сильнее надо обосновывать цену.
A11: G. Боли и JTBD | B11: =SUM(Данные!C61:C70) -> 0 | C11: =SUM(Данные!D61:D70) -> 0 | D11: =SUM(Данные!F61:F70) -> 0 | E11: =SUM(Данные!H61:H70) -> 0 | F11: =IFERROR(B11/MAX(E11,1),0) -> 0 | G11: Проверка маркетинговых аргументов цифрой, а не гипотезой.
A12: H. Городская альтернатива | B12: =SUM(Данные!C71:C76) -> 0 | C12: =SUM(Данные!D71:D76) -> 0 | D12: =SUM(Данные!F71:F76) -> 0 | E12: =SUM(Данные!H71:H76) -> 0 | F12: =IFERROR(B12/MAX(E12,1),0) -> 0 | G12: Конкуренция за тот же бюджет внутри города.
A13: I. Отток капитала | B13: =SUM(Данные!C77:C81) -> 0 | C13: =SUM(Данные!D77:D81) -> 0 | D13: =SUM(Данные!F77:F81) -> 0 | E13: =SUM(Данные!H77:H81) -> 0 | F13: =IFERROR(B13/MAX(E13,1),0) -> 0 | G13: Сильнейший конкурент: деньги уезжают. Сравнивать с блоком B.
A14: J. Бренды конкурентов | B14: =SUM(Данные!C82:C84) -> 0 | C14: =SUM(Данные!D82:D84) -> 0 | D14: =SUM(Данные!F82:F84) -> 0 | E14: =SUM(Данные!H82:H84) -> 0 | F14: =IFERROR(B14/MAX(E14,1),0) -> 0 | G14: Baseline для будущего замера собственного бренда.
A15: ИТОГО | B15: =SUM(B5:B14) -> 0 | C15: =SUM(C5:C14) -> 0 | D15: =SUM(D5:D14) -> 0 | E15: =SUM(E5:E14) -> 0
A18: Ключевые соотношения и вердикты
A19: Показатель | B19: Значение | G19: Вердикт
A20: Объём категории (блок A), Чита + край | B20: =B5+D5 -> 0 | G20: =IF(B20<300,"Категории не существует. Первый год бюджета — на её создание, перформанс не сработает. Вы заходите первым.",IF(B20<1500,"Категория зарождается. Окно для захвата открыто.","Категория сформирована — проверить, кем занята.")) -> Категории не существует. Первый год бюджета — на её создание, перформанс не сработает. Вы заходите первым.
A21: Продукт / Категория | B21: =IFERROR(B6/MAX(B5,1),0) -> 0 | G21: =IF(B20>10,"Рынок ищет дом, а не посёлок. Продавать дом, среду отдавать бонусом — иначе объявления не найдут.","Категория узнаваема, можно продавать посёлок как таковой.") -> Категория узнаваема, можно продавать посёлок как таковой.
A22: Земля + Самострой / Продукт | B22: =IFERROR((B7+B10)/MAX(B6,1),0) -> 0 | G22: =IF(B20>1.5,"Доминирует сценарий «куплю землю и построю сам». Продукт обязан объяснять переплату к самострою.","Готовый дом — основной сценарий, переплату обосновать проще.") -> Готовый дом — основной сценарий, переплату обосновать проще.
A23: Ипотечные триггеры / Продукт | B23: =IFERROR(B9/MAX(B6,1),0) -> 0 | G23: =IF(B20>0.3,"Спрос ипотечный. Ядро линейки жёстко под лимит ДВ-ипотеки: дом 11–14 млн, площадь строго от 60 кв.м.","Ипотека не драйвер — сегмент наличных, проверить ёмкость по Росреестру.") -> Ипотека не драйвер — сегмент наличных, проверить ёмкость по Росреестру.
A24: Отток капитала / Продукт | B24: =IFERROR(B13/MAX(B6,1),0) -> 0 | G24: =IF(B20>1,"Деньги уезжают из региона. Главный конкурент — не посёлок, а квартира в другом городе. Ёмкость верхнего сегмента ниже расчётной.","Отток умеренный, капитал остаётся в регионе.") -> Отток умеренный, капитал остаётся в регионе.
A25: Карповка / Смоленка (широкое) | B25: =IFERROR(Данные!C28/MAX(Данные!C30,1),0) -> 0 | G25: =IF(B25<0.5,"Локация вне зоны внимания рынка. Заложить бюджет и срок на её «открытие» — это отдельная статья.","Локация в поле зрения рынка.") -> Локация вне зоны внимания рынка. Заложить бюджет и срок на её «открытие» — это отдельная статья.
A27: Пороги в формулах — экспертная оценка для города размера Читы, а не отраслевой стандарт. Их следует пересмотреть после первого сбора.

Sheet Пороги решения
B2: Как читать результат
B4: Что видите | C4: Что это значит для проекта
B5: Блок A суммарно менее 300/мес по краю | C5: Категории не существует. Первый год бюджета уходит на её создание, перформанс-каналы не работают. Это аргумент в пользу того, что вы заходите первым.
B6: Блок B в 10+ раз больше блока A | C6: Рынок ищет дом, а не посёлок. Продавать нужно дом, среду отдавать как бонус в креативе.
B7: Блок E растёт год к году | C7: Платёжеспособный спрос формируется ипотекой. Ядро линейки — под лимит ДВ-ипотеки: 9 млн кредита при площади от 60 кв.м, объект до 11,25 млн.
B8: Блок I сопоставим с блоком B | C8: Отток капитала реален. Ёмкость верхнего сегмента ещё меньше расчётной, гипотезу 35–40 млн вычёркивать.
B9: Карповка заметно ниже Смоленки и Засопки | C9: Локация не в зоне внимания рынка. Придётся закладывать бюджет на её «открытие» — отдельная статья затрат и отдельный срок продаж.
B10: Блоки C и F вместе больше блока B | C10: Доминирует сценарий самостроя. Продукт обязан объяснять переплату к варианту «купил участок за 1,4 млн и построил за 12».
B11: Блок G: высокая частотность по воде | C11: Водная боль подтверждена. Водоподготовка идёт в оффер первым аргументом, а не строчкой в спецификации.
B13: Чего эти данные НЕ показывают
B14: Платёжеспособность | C14: Частотность измеряет интерес, а не деньги. Сверять с количеством сделок по данным Росреестра.
B15: Сделки вне площадок | C15: В городах размера Читы дорогие сделки идут через знакомых и подрядчика. Верхний сегмент может быть невидим и в поиске, и на Авито.
B16: Будущий спрос | C16: Wordstat показывает прошлое. Для проекта со сроком реализации 3–5 лет это только отправная точка.
